merchant_rest_service/__init__.py
merchant_rest_service/apibase.py
merchant_rest_service/merchant_client_core.py
merchant_rest_service/version.py
merchant_rest_service-0.0.1.dist-info/AUTHORS.rst
merchant_rest_service-0.0.1.dist-info/LICENSE
merchant_rest_service-0.0.1.dist-info/METADATA
merchant_rest_service-0.0.1.dist-info/WHEEL
merchant_rest_service-0.0.1.dist-info/entry_points.txt
merchant_rest_service-0.0.1.dist-info/top_level.txt
merchant_rest_service-0.0.1.dist-info/RECORD
