Metadata-Version: 2.1
Name: merchant-rest-service
Version: 0.0.1
Summary: When you need to make use of Paga Merchant Service API, using our libraries to interact with the APIs makes your integration fast as most of the API logic has been handled when using the Paga Merchant Libraries
Home-page: https://https://github.com/pagadevcomm/merchant_rest_service.git/pagadevcomm/merchant_rest_service
Author: Paga Developer Community
Author-email: devcomm@paga.com
License: MIT
Project-URL: Changelog, https://https://github.com/pagadevcomm/merchant_rest_service.git/pagadevcomm/merchant_rest_service/blob/master/CHANGELOG.rst
Project-URL: Issue Tracker, https://https://github.com/pagadevcomm/merchant_rest_service.git/pagadevcomm/merchant_rest_service/issues
Platform: UNKNOWN
Classifier: Development Status :: 5 - Production/Stable
Classifier: Intended Audience :: Developers
Classifier: License :: OSI Approved :: MIT License
Classifier: Operating System :: Unix
Classifier: Operating System :: POSIX
Classifier: Operating System :: Microsoft :: Windows
Classifier: Programming Language :: Python
Classifier: Programming Language :: Python :: 2.7
Classifier: Programming Language :: Python :: 3
Classifier: Programming Language :: Python :: 3.5
Classifier: Programming Language :: Python :: 3.6
Classifier: Programming Language :: Python :: 3.7
Classifier: Programming Language :: Python :: 3.8
Classifier: Programming Language :: Python :: Implementation :: CPython
Classifier: Programming Language :: Python :: Implementation :: PyPy
Classifier: Topic :: Utilities
Requires-Python: >=2.7, !=3.0.*, !=3.1.*, !=3.2.*, !=3.3.*, !=3.4.*
